LICENSE
LICENSES.md
MANIFEST.in
README.md
setup.cfg
setup.py
./mmcv/ops/csrc/pytorch/active_rotated_filter.cpp
./mmcv/ops/csrc/pytorch/assign_score_withk.cpp
./mmcv/ops/csrc/pytorch/ball_query.cpp
./mmcv/ops/csrc/pytorch/bbox_overlaps.cpp
./mmcv/ops/csrc/pytorch/bezier_align.cpp
./mmcv/ops/csrc/pytorch/bias_act.cpp
./mmcv/ops/csrc/pytorch/border_align.cpp
./mmcv/ops/csrc/pytorch/box_iou_quadri.cpp
./mmcv/ops/csrc/pytorch/box_iou_rotated.cpp
./mmcv/ops/csrc/pytorch/carafe.cpp
./mmcv/ops/csrc/pytorch/carafe_naive.cpp
./mmcv/ops/csrc/pytorch/chamfer_distance.cpp
./mmcv/ops/csrc/pytorch/contour_expand.cpp
./mmcv/ops/csrc/pytorch/convex_iou.cpp
./mmcv/ops/csrc/pytorch/correlation.cpp
./mmcv/ops/csrc/pytorch/deform_conv.cpp
./mmcv/ops/csrc/pytorch/deform_roi_pool.cpp
./mmcv/ops/csrc/pytorch/diff_iou_rotated.cpp
./mmcv/ops/csrc/pytorch/filtered_lrelu.cpp
./mmcv/ops/csrc/pytorch/focal_loss.cpp
./mmcv/ops/csrc/pytorch/furthest_point_sample.cpp
./mmcv/ops/csrc/pytorch/fused_bias_leakyrelu.cpp
./mmcv/ops/csrc/pytorch/fused_spconv_ops.cpp
./mmcv/ops/csrc/pytorch/gather_points.cpp
./mmcv/ops/csrc/pytorch/group_points.cpp
./mmcv/ops/csrc/pytorch/info.cpp
./mmcv/ops/csrc/pytorch/iou3d.cpp
./mmcv/ops/csrc/pytorch/knn.cpp
./mmcv/ops/csrc/pytorch/masked_conv2d.cpp
./mmcv/ops/csrc/pytorch/min_area_polygons.cpp
./mmcv/ops/csrc/pytorch/modulated_deform_conv.cpp
./mmcv/ops/csrc/pytorch/ms_deform_attn.cpp
./mmcv/ops/csrc/pytorch/nms.cpp
./mmcv/ops/csrc/pytorch/nms_quadri.cpp
./mmcv/ops/csrc/pytorch/nms_rotated.cpp
./mmcv/ops/csrc/pytorch/pixel_group.cpp
./mmcv/ops/csrc/pytorch/points_in_boxes.cpp
./mmcv/ops/csrc/pytorch/points_in_polygons.cpp
./mmcv/ops/csrc/pytorch/prroi_pool.cpp
./mmcv/ops/csrc/pytorch/psamask.cpp
./mmcv/ops/csrc/pytorch/pybind.cpp
./mmcv/ops/csrc/pytorch/riroi_align_rotated.cpp
./mmcv/ops/csrc/pytorch/roi_align.cpp
./mmcv/ops/csrc/pytorch/roi_align_rotated.cpp
./mmcv/ops/csrc/pytorch/roi_pool.cpp
./mmcv/ops/csrc/pytorch/roiaware_pool3d.cpp
mmcv_open.egg-info/PKG-INFO
mmcv_open.egg-info/SOURCES.txt
mmcv_open.egg-info/dependency_links.txt
mmcv_open.egg-info/not-zip-safe
mmcv_open.egg-info/requires.txt
mmcv_open.egg-info/top_level.txt
